[{"name": "class", "pose": "Unspecified", "truncated": 0, "difficult": 0, "bndbox": {"xmin": 93, "ymin": 42, "xmax": 102, "ymax": 49}}, {"name": "dl_number", "pose": "Unspecified", "truncated": 0, "difficult": 0, "bndbox": {"xmin": 94, "ymin": 50, "xmax": 140, "ymax": 61}}, {"name": "issue_date", "pose": "Unspecified", "truncated": 0, "difficult": 0, "bndbox": {"xmin": 163, "ymin": 46, "xmax": 204, "ymax": 56}}, {"name": "date_of_birth", "pose": "Unspecified", "truncated": 0, "difficult": 0, "bndbox": {"xmin": 163, "ymin": 57, "xmax": 202, "ymax": 68}}, {"name": "name", "pose": "Unspecified", "truncated": 0, "difficult": 0, "bndbox": {"xmin": 73, "ymin": 60, "xmax": 115, "ymax": 79}}, {"name": "address", "pose": "Unspecified", "truncated": 0, "difficult": 0, "bndbox": {"xmin": 73, "ymin": 78, "xmax": 153, "ymax": 96}}, {"name": "sex", "pose": "Unspecified", "truncated": 0, "difficult": 0, "bndbox": {"xmin": 84, "ymin": 107, "xmax": 92, "ymax": 114}}, {"name": "exp_date", "pose": "Unspecified", "truncated": 0, "difficult": 0, "bndbox": {"xmin": 161, "ymin": 111, "xmax": 194, "ymax": 121}}, {"name": "height", "pose": "Unspecified", "truncated": 0, "difficult": 0, "bndbox": {"xmin": 85, "ymin": 112, "xmax": 102, "ymax": 123}}, {"name": "eyes", "pose": "Unspecified", "truncated": 0, "difficult": 0, "bndbox": {"xmin": 125, "ymin": 115, "xmax": 144, "ymax": 125}}]