[{"name": "name", "pose": "Unspecified", "truncated": 0, "difficult": 0, "bndbox": {"xmin": 163, "ymin": 65, "xmax": 266, "ymax": 81}}, {"name": "dl_number", "pose": "Unspecified", "truncated": 0, "difficult": 0, "bndbox": {"xmin": 184, "ymin": 41, "xmax": 375, "ymax": 64}}, {"name": "address", "pose": "Unspecified", "truncated": 0, "difficult": 0, "bndbox": {"xmin": 164, "ymin": 85, "xmax": 341, "ymax": 115}}, {"name": "date_of_birth", "pose": "Unspecified", "truncated": 0, "difficult": 0, "bndbox": {"xmin": 179, "ymin": 123, "xmax": 244, "ymax": 147}}, {"name": "sex", "pose": "Unspecified", "truncated": 0, "difficult": 0, "bndbox": {"xmin": 243, "ymin": 129, "xmax": 261, "ymax": 143}}, {"name": "height", "pose": "Unspecified", "truncated": 0, "difficult": 0, "bndbox": {"xmin": 264, "ymin": 132, "xmax": 299, "ymax": 146}}, {"name": "issue_date", "pose": "Unspecified", "truncated": 0, "difficult": 0, "bndbox": {"xmin": 181, "ymin": 158, "xmax": 242, "ymax": 171}}, {"name": "exp_date", "pose": "Unspecified", "truncated": 0, "difficult": 0, "bndbox": {"xmin": 258, "ymin": 160, "xmax": 311, "ymax": 173}}]