<annotation>
	<folder>converted-images</folder>
	<filename>139.jpg</filename>
	<path>C:\Users\Zohra\Downloads\more-dl-images\converted-images\139.jpg</path>
	<source>
		<database>Unknown</database>
	</source>
	<size>
		<width>345</width>
		<height>217</height>
		<depth>3</depth>
	</size>
	<segmented>0</segmented>
	<object>
		<name>dl_number</name>
		<pose>Unspecified</pose>
		<truncated>0</truncated>
		<difficult>0</difficult>
		<bndbox>
			<xmin>156</xmin>
			<ymin>50</ymin>
			<xmax>225</xmax>
			<ymax>67</ymax>
		</bndbox>
	</object>
	<object>
		<name>date_of_birth</name>
		<pose>Unspecified</pose>
		<truncated>0</truncated>
		<difficult>0</difficult>
		<bndbox>
			<xmin>155</xmin>
			<ymin>67</ymin>
			<xmax>222</xmax>
			<ymax>82</ymax>
		</bndbox>
	</object>
	<object>
		<name>issue_date</name>
		<pose>Unspecified</pose>
		<truncated>0</truncated>
		<difficult>0</difficult>
		<bndbox>
			<xmin>265</xmin>
			<ymin>53</ymin>
			<xmax>333</xmax>
			<ymax>67</ymax>
		</bndbox>
	</object>
	<object>
		<name>exp_date</name>
		<pose>Unspecified</pose>
		<truncated>0</truncated>
		<difficult>0</difficult>
		<bndbox>
			<xmin>268</xmin>
			<ymin>69</ymin>
			<xmax>329</xmax>
			<ymax>80</ymax>
		</bndbox>
	</object>
	<object>
		<name>name</name>
		<pose>Unspecified</pose>
		<truncated>0</truncated>
		<difficult>0</difficult>
		<bndbox>
			<xmin>122</xmin>
			<ymin>84</ymin>
			<xmax>183</xmax>
			<ymax>112</ymax>
		</bndbox>
	</object>
	<object>
		<name>address</name>
		<pose>Unspecified</pose>
		<truncated>0</truncated>
		<difficult>0</difficult>
		<bndbox>
			<xmin>122</xmin>
			<ymin>120</ymin>
			<xmax>244</xmax>
			<ymax>144</ymax>
		</bndbox>
	</object>
	<object>
		<name>class</name>
		<pose>Unspecified</pose>
		<truncated>0</truncated>
		<difficult>0</difficult>
		<bndbox>
			<xmin>150</xmin>
			<ymin>143</ymin>
			<xmax>162</xmax>
			<ymax>156</ymax>
		</bndbox>
	</object>
	<object>
		<name>restrictions</name>
		<pose>Unspecified</pose>
		<truncated>0</truncated>
		<difficult>0</difficult>
		<bndbox>
			<xmin>180</xmin>
			<ymin>155</ymin>
			<xmax>220</xmax>
			<ymax>172</ymax>
		</bndbox>
	</object>
	<object>
		<name>height</name>
		<pose>Unspecified</pose>
		<truncated>0</truncated>
		<difficult>0</difficult>
		<bndbox>
			<xmin>140</xmin>
			<ymin>169</ymin>
			<xmax>178</xmax>
			<ymax>185</ymax>
		</bndbox>
	</object>
	<object>
		<name>eyes</name>
		<pose>Unspecified</pose>
		<truncated>0</truncated>
		<difficult>0</difficult>
		<bndbox>
			<xmin>305</xmin>
			<ymin>170</ymin>
			<xmax>333</xmax>
			<ymax>184</ymax>
		</bndbox>
	</object>
	<object>
		<name>sex</name>
		<pose>Unspecified</pose>
		<truncated>0</truncated>
		<difficult>0</difficult>
		<bndbox>
			<xmin>322</xmin>
			<ymin>142</ymin>
			<xmax>330</xmax>
			<ymax>155</ymax>
		</bndbox>
	</object>
</annotation>
