<annotation>
	<folder>dl-images</folder>
	<filename>93.jpg</filename>
	<path>C:\Users\Zohra\Downloads\id\id\dl-images\93.jpg</path>
	<source>
		<database>Unknown</database>
	</source>
	<size>
		<width>640</width>
		<height>360</height>
		<depth>3</depth>
	</size>
	<segmented>0</segmented>
	<object>
		<name>dl_number</name>
		<pose>Unspecified</pose>
		<truncated>0</truncated>
		<difficult>0</difficult>
		<bndbox>
			<xmin>273</xmin>
			<ymin>85</ymin>
			<xmax>494</xmax>
			<ymax>115</ymax>
		</bndbox>
	</object>
	<object>
		<name>class</name>
		<pose>Unspecified</pose>
		<truncated>0</truncated>
		<difficult>0</difficult>
		<bndbox>
			<xmin>535</xmin>
			<ymin>77</ymin>
			<xmax>550</xmax>
			<ymax>100</ymax>
		</bndbox>
	</object>
	<object>
		<name>name</name>
		<pose>Unspecified</pose>
		<truncated>0</truncated>
		<difficult>0</difficult>
		<bndbox>
			<xmin>235</xmin>
			<ymin>113</ymin>
			<xmax>308</xmax>
			<ymax>141</ymax>
		</bndbox>
	</object>
	<object>
		<name>address</name>
		<pose>Unspecified</pose>
		<truncated>0</truncated>
		<difficult>0</difficult>
		<bndbox>
			<xmin>239</xmin>
			<ymin>142</ymin>
			<xmax>463</xmax>
			<ymax>167</ymax>
		</bndbox>
	</object>
	<object>
		<name>date_of_birth</name>
		<pose>Unspecified</pose>
		<truncated>0</truncated>
		<difficult>0</difficult>
		<bndbox>
			<xmin>274</xmin>
			<ymin>164</ymin>
			<xmax>369</xmax>
			<ymax>188</ymax>
		</bndbox>
	</object>
	<object>
		<name>sex</name>
		<pose>Unspecified</pose>
		<truncated>0</truncated>
		<difficult>0</difficult>
		<bndbox>
			<xmin>405</xmin>
			<ymin>169</ymin>
			<xmax>426</xmax>
			<ymax>186</ymax>
		</bndbox>
	</object>
	<object>
		<name>exp_date</name>
		<pose>Unspecified</pose>
		<truncated>0</truncated>
		<difficult>0</difficult>
		<bndbox>
			<xmin>275</xmin>
			<ymin>188</ymin>
			<xmax>355</xmax>
			<ymax>204</ymax>
		</bndbox>
	</object>
	<object>
		<name>height</name>
		<pose>Unspecified</pose>
		<truncated>0</truncated>
		<difficult>0</difficult>
		<bndbox>
			<xmin>404</xmin>
			<ymin>189</ymin>
			<xmax>455</xmax>
			<ymax>202</ymax>
		</bndbox>
	</object>
	<object>
		<name>restrictions</name>
		<pose>Unspecified</pose>
		<truncated>0</truncated>
		<difficult>0</difficult>
		<bndbox>
			<xmin>275</xmin>
			<ymin>202</ymin>
			<xmax>329</xmax>
			<ymax>221</ymax>
		</bndbox>
	</object>
	<object>
		<name>issue_date</name>
		<pose>Unspecified</pose>
		<truncated>0</truncated>
		<difficult>0</difficult>
		<bndbox>
			<xmin>277</xmin>
			<ymin>248</ymin>
			<xmax>351</xmax>
			<ymax>265</ymax>
		</bndbox>
	</object>
</annotation>
